LICENSE
sphinxcontrib_data_pipeline/__init__.py
sphinxcontrib_data_pipeline/data_product.py
sphinxcontrib_data_pipeline/driver.py
sphinxcontrib_data_pipeline/external_data_products.py
sphinxcontrib_data_pipeline/external_drivers.py
sphinxcontrib_data_pipeline/parsers/__init__.py
sphinxcontrib_data_pipeline/parsers/example_yaml_parser.py
sphinxcontrib_data_pipeline/pipeline.py
sphinxcontrib_data_pipeline/remote_files.py
sphinxcontrib_data_pipeline/utils.py
sphinxcontrib_data_pipeline/workflow_parser.py
sphinxcontrib_data_pipeline-0.3.0.dist-info/LICENSE
sphinxcontrib_data_pipeline-0.3.0.dist-info/METADATA
sphinxcontrib_data_pipeline-0.3.0.dist-info/WHEEL
sphinxcontrib_data_pipeline-0.3.0.dist-info/RECORD
